{
  "date": "2026-05-07",
  "category": "book",
  "article_count": 184,
  "source_count": 7,
  "matched_count": 83,
  "top_entities": [
    {
      "name": "Genre",
      "count": 86
    },
    {
      "name": "Author",
      "count": 20
    },
    {
      "name": "Award",
      "count": 16
    },
    {
      "name": "BookType",
      "count": 7
    },
    {
      "name": "Publisher",
      "count": 2
    },
    {
      "name": "BookEvent",
      "count": 2
    }
  ],
  "sources": {
    "New York Times Books": 27,
    "Book Riot": 45,
    "Literary Hub": 42,
    "Publishing Perspectives": 9,
    "NPR Books": 9,
    "The Guardian Books": 15,
    "Publishers Weekly": 37
  },
  "generated_at": "2026-05-07T13:35:12.949059+09:00"
}