{
  "date": "2026-03-24",
  "category": "book",
  "article_count": 53,
  "source_count": 4,
  "matched_count": 24,
  "top_entities": [
    {
      "name": "Genre",
      "count": 66
    },
    {
      "name": "Award",
      "count": 16
    },
    {
      "name": "BookType",
      "count": 11
    },
    {
      "name": "Publisher",
      "count": 5
    }
  ],
  "sources": {
    "Kirkus Reviews": 30,
    "알라딘 신간 (경제경영)": 6,
    "알라딘 신간 (소설)": 16,
    "알라딘 신간 (자기계발)": 1
  },
  "generated_at": "2026-03-24T13:46:16.734870+09:00"
}